odoo10_addon_product_online_category-10.0.1.0.0.99.dev3-py3.8-nspkg.pth
odoo/addons/product_online_category/README.rst
odoo/addons/product_online_category/__init__.py
odoo/addons/product_online_category/__manifest__.py
odoo/addons/product_online_category/i18n/product_online_category.pot
odoo/addons/product_online_category/models/__init__.py
odoo/addons/product_online_category/models/product.py
odoo10_addon_product_online_category-10.0.1.0.0.99.dev3.dist-info/METADATA
odoo10_addon_product_online_category-10.0.1.0.0.99.dev3.dist-info/WHEEL
odoo10_addon_product_online_category-10.0.1.0.0.99.dev3.dist-info/namespace_packages.txt
odoo10_addon_product_online_category-10.0.1.0.0.99.dev3.dist-info/top_level.txt
odoo10_addon_product_online_category-10.0.1.0.0.99.dev3.dist-info/RECORD
